{
    "datetime": "2020-04-13T15:14:48.763943+00:00",
    "cough_detected": "0.8267",
    "age": "18",
    "gender": "male",
    "respiratory_condition": "True",
    "fever_muscle_pain": "True",
    "status": "COVID-19",
    "expert_labels_1": {
        "quality": "ok",
        "cough_type": "dry",
        "dyspnea": "False",
        "wheezing": "False",
        "stridor": "False",
        "choking": "False",
        "congestion": "False",
        "nothing": "True",
        "diagnosis": "lower_infection",
        "severity": "mild"
    },
    "expert_labels_2": {
        "quality": "ok",
        "cough_type": "dry",
        "dyspnea": "False",
        "wheezing": "False",
        "stridor": "False",
        "choking": "False",
        "congestion": "False",
        "nothing": "True",
        "diagnosis": "COVID-19",
        "severity": "mild"
    },
    "expert_labels_3": {
        "quality": "good",
        "cough_type": "dry",
        "dyspnea": "False",
        "wheezing": "False",
        "stridor": "False",
        "choking": "False",
        "congestion": "False",
        "nothing": "True",
        "diagnosis": "upper_infection",
        "severity": "mild"
    },
    "expert_labels_4": {
        "quality": "good",
        "cough_type": "dry",
        "dyspnea": "False",
        "wheezing": "False",
        "stridor": "False",
        "choking": "False",
        "congestion": "False",
        "nothing": "True",
        "diagnosis": "healthy_cough",
        "severity": "pseudocough"
    }
}