{
    "datetime": "2020-04-10T04:37:49.199245+00:00",
    "cough_detected": "0.9957",
    "age": "37",
    "gender": "female",
    "respiratory_condition": "False",
    "fever_muscle_pain": "False",
    "status": "COVID-19",
    "expert_labels_2": {
        "quality": "good",
        "cough_type": "dry",
        "dyspnea": "False",
        "wheezing": "False",
        "stridor": "False",
        "choking": "False",
        "congestion": "False",
        "nothing": "True",
        "diagnosis": "upper_infection",
        "severity": "mild"
    }
}