{
    "datetime": "2020-04-13T09:45:31.202978+00:00",
    "cough_detected": "0.9714",
    "latitude": "37.2",
    "longitude": "-94.6",
    "age": "25",
    "gender": "female",
    "respiratory_condition": "False",
    "fever_muscle_pain": "True",
    "status": "symptomatic",
    "expert_labels_1": {
        "quality": "ok",
        "cough_type": "dry",
        "dyspnea": "False",
        "wheezing": "False",
        "stridor": "False",
        "choking": "False",
        "congestion": "False",
        "nothing": "True",
        "diagnosis": "COVID-19",
        "severity": "severe"
    }
}