{
    "datetime": "2020-10-28T01:44:26.455764+00:00",
    "cough_detected": "0.9905",
    "age": "12",
    "gender": "male",
    "respiratory_condition": "True",
    "fever_muscle_pain": "False",
    "status": "healthy",
    "expert_labels_4": {
        "quality": "ok",
        "cough_type": "dry",
        "dyspnea": "False",
        "wheezing": "False",
        "stridor": "False",
        "choking": "False",
        "congestion": "False",
        "nothing": "True",
        "diagnosis": "upper_infection",
        "severity": "mild"
    }
}